xspawn/__init__.py
xspawn/__main__.py
xspawn/adopt.py
xspawn/cli.py
xspawn/petition.py
xspawn-0.1.0.dist-info/METADATA
xspawn-0.1.0.dist-info/WHEEL
xspawn-0.1.0.dist-info/entry_points.txt
xspawn-0.1.0.dist-info/top_level.txt
xspawn-0.1.0.dist-info/RECORD
