Metadata-Version: 2.4
Name: xspawn
Version: 0.1.0
Summary: XKO spawn petition + adoption helper (CLI)
Author: Rook Services Inc.
License: MIT
Requires-Python: >=3.10
